range_css_compiler/__init__.py
range_css_compiler/test.py
range_css_compiler/parts/gen_compiled_rcss.py
range_css_compiler/parts/pypi_tool_file_binder.py
range_css_compiler/parts/to_qp_mat_js.py
range_css_compiler/parts/yaml_style_to_equid.py
range_css_compiler-0.2.2.dist-info/METADATA
range_css_compiler-0.2.2.dist-info/WHEEL
range_css_compiler-0.2.2.dist-info/entry_points.txt
range_css_compiler-0.2.2.dist-info/top_level.txt
range_css_compiler-0.2.2.dist-info/RECORD
