Metadata-Version: 2.1
Name: range-css-compiler
Version: 0.2.2
Summary: More intuitive HTML placement and assignment tool than CSS.
Home-page: https://github.co.jp/
Author: le_lattelle
Author-email: g.tiger.ml@gmail.com
License: CC0 v1.0
Platform: UNKNOWN
Classifier: Programming Language :: Python :: 3
Classifier: Topic :: Software Development :: Libraries
Classifier: License :: CC0 1.0 Universal (CC0 1.0) Public Domain Dedication
Requires-Dist: relpath
Requires-Dist: ezpip
Requires-Dist: sout
Requires-Dist: fies
Requires-Dist: tqdm
Requires-Dist: equid
Requires-Dist: indent-template
Requires-Dist: ezptn
